LICENSE.txt
MANIFEST.in
README.md
setup.cfg
setup.py
django_hidefield.egg-info/PKG-INFO
django_hidefield.egg-info/SOURCES.txt
django_hidefield.egg-info/dependency_links.txt
django_hidefield.egg-info/top_level.txt
hidefield/__init__.py
hidefield/apps.py
hidefield/fields.py
hidefield/static/hidefield/hidefield.js
hidefield/templates/hidefield/hidefield.html