Metadata-Version: 2.1
Name: django-hidefield
Version: 0.2.0
Summary: hide fields in django admin
Home-page: https://github.com/jerch/django-hidefield
Author: Joerg Breitbart
Author-email: j.breitbart@netzkolchose.de
License: UNKNOWN
Download-URL: https://github.com/jerch/django-hidefield/archive/0.2.0.tar.gz
Keywords: django,widget,admin,field,hide
Platform: UNKNOWN
Classifier: Development Status :: 4 - Beta
Classifier: Intended Audience :: Developers
Classifier: Topic :: Database
Classifier: Topic :: Database :: Front-Ends
Classifier: Topic :: Software Development :: Libraries
Classifier: Framework :: Django
Classifier: Framework :: Django :: 3.2
Classifier: Framework :: Django :: 4.2
Classifier: License :: OSI Approved :: MIT License
Classifier: Programming Language :: Python :: 3
Classifier: Programming Language :: Python :: 3.7
Classifier: Programming Language :: Python :: 3.8
Classifier: Programming Language :: Python :: 3.9
Classifier: Programming Language :: Python :: 3.10
Classifier: Programming Language :: Python :: 3.11
License-File: LICENSE.txt
